shyaml.py
shyaml-0.6.1.dist-info/DESCRIPTION.rst
shyaml-0.6.1.dist-info/LICENSE.txt
shyaml-0.6.1.dist-info/METADATA
shyaml-0.6.1.dist-info/RECORD
shyaml-0.6.1.dist-info/WHEEL
shyaml-0.6.1.dist-info/entry_points.txt
shyaml-0.6.1.dist-info/metadata.json
shyaml-0.6.1.dist-info/top_level.txt
