Metadata-Version: 1.1
Name: shyaml
Version: 0.6.1
Summary: YAML for command line
Home-page: http://github.com/0k/shyaml
Author: Valentin Lab
Author-email: valentin.lab@kalysto.org
License: BSD 3-Clause License
Platform: UNKNOWN
Classifier: Programming Language :: Python
Classifier: Environment :: Console
Classifier: Intended Audience :: Developers
Classifier: License :: OSI Approved :: BSD License
Classifier: Topic :: Software Development
Classifier: Topic :: Software Development :: Libraries :: Python Modules
Classifier: Development Status :: 5 - Production/Stable
Classifier: Programming Language :: Python :: 2
Classifier: Programming Language :: Python :: 2.7
Classifier: Programming Language :: Python :: 3
Classifier: Programming Language :: Python :: 3.3
Classifier: Programming Language :: Python :: 3.4
Classifier: Programming Language :: Python :: 3.5
Classifier: Programming Language :: Python :: 3.6
Classifier: Programming Language :: Python :: 3.7
